amapy_server/__init__.py
amapy_server/app.py
amapy_server/db.py
amapy_server/main.py
amapy_server/plugins.py
amapy_server/run_gunicorn.py
amapy_server/asset_client/__init__.py
amapy_server/asset_client/asset.py
amapy_server/asset_client/asset_class.py
amapy_server/asset_client/asset_object.py
amapy_server/asset_client/asset_version.py
amapy_server/asset_client/asset_writer.py
amapy_server/asset_client/base_asset.py
amapy_server/asset_client/commit_mixin.py
amapy_server/asset_client/dict_diff.py
amapy_server/asset_client/exceptions.py
amapy_server/asset_client/serializable.py
amapy_server/asset_client/state.py
amapy_server/asset_client/versioning.py
amapy_server/asset_client/contents/__init__.py
amapy_server/asset_client/contents/content.py
amapy_server/asset_client/contents/content_factory.py
amapy_server/asset_client/contents/content_set.py
amapy_server/asset_client/contents/content_uploader.py
amapy_server/asset_client/contents/db_content.py
amapy_server/asset_client/contents/docker_content.py
amapy_server/asset_client/contents/file_content.py
amapy_server/asset_client/contents/gcs_content.py
amapy_server/asset_client/contents/url_content.py
amapy_server/asset_client/contents/tests/__init__.py
amapy_server/asset_client/contents/tests/test_content_factory.py
amapy_server/asset_client/contents/tests/test_content_uploader.py
amapy_server/asset_client/contents/tests/test_docker_content.py
amapy_server/asset_client/contents/tests/test_file_content.py
amapy_server/asset_client/contents/tests/test_gcs_content.py
amapy_server/asset_client/objects/__init__.py
amapy_server/asset_client/objects/object.py
amapy_server/asset_client/objects/object_set.py
amapy_server/asset_client/objects/objects_diff.py
amapy_server/asset_client/objects/tests/__init__.py
amapy_server/asset_client/objects/tests/test_object.py
amapy_server/asset_client/objects/tests/test_object_set.py
amapy_server/asset_client/objects/tests/test_objects_diff.py
amapy_server/asset_client/objects/tests/test_set.py
amapy_server-1.0.2.dist-info/METADATA
amapy_server-1.0.2.dist-info/WHEEL
amapy_server-1.0.2.dist-info/entry_points.txt
amapy_server-1.0.2.dist-info/top_level.txt
amapy_server-1.0.2.dist-info/RECORD
